{
    "%vlocity_namespace%__Active__c": true,
    "%vlocity_namespace%__InternalNotes__c": "Message re: Bundled Discount",
    "%vlocity_namespace%__Level__c": 1,
    "%vlocity_namespace%__OmniScriptId__c": {
        "Name": "SG Quoting - Non NY",
        "VlocityDataPackType": "VlocityMatchingKeyObject",
        "VlocityMatchingRecordSourceKey": "%vlocity_namespace%__OmniScript__c/SG Quoting/Non-NY/English",
        "VlocityRecordSObjectType": "%vlocity_namespace%__OmniScript__c"
    },
    "%vlocity_namespace%__Order__c": 2,
    "%vlocity_namespace%__ParentElementId__c": {
        "%vlocity_namespace%__OmniScriptId__c": "%vlocity_namespace%__OmniScript__c/SG Quoting/Non-NY/English",
        "Name": "SelectVisionPlans",
        "VlocityDataPackType": "VlocityMatchingKeyObject",
        "VlocityMatchingRecordSourceKey": "%vlocity_namespace%__Element__c/%vlocity_namespace%__OmniScript__c/SG Quoting/Non-NY/English/SelectVisionPlans",
        "VlocityRecordSObjectType": "%vlocity_namespace%__Element__c"
    },
    "%vlocity_namespace%__ParentElementName__c": "SelectVisionPlans",
    "%vlocity_namespace%__ParentElementType__c": "Step",
    "%vlocity_namespace%__PropertySet__c": {
        "HTMLTemplateId": "",
        "controlWidth": 12,
        "dataJSON": false,
        "disOnTplt": false,
        "documentNames": [
            "Green"
        ],
        "label": "MedicalLockDisclaimer_Vision",
        "show": {
            "group": {
                "operator": "AND",
                "rules": [
                    {
                        "condition": "<>",
                        "data": "NY",
                        "field": "SelectedState"
                    }
                ]
            }
        },
        "text": "<p><span style=\"color: #ff0000;\">To apply the Medical Lock (packaged enrollment) discount, all members enrolled in an&nbsp;%AnthemBrand%&nbsp;medical plan must enroll in vision. Vision tiering must be identical on the medical and vision plans. Example: Enrollees with Single medical coverage must also have Single vision coverage; enrollees with Family medical coverage must also have Family vision coverage.</span></p>"
    },
    "%vlocity_namespace%__ReusableOmniScript__c": true,
    "%vlocity_namespace%__Type__c": "Text Block",
    "Name": "MedicalLockDisclaimer_Vision",
    "VlocityDataPackType": "SObject",
    "VlocityRecordSObjectType": "%vlocity_namespace%__Element__c",
    "VlocityRecordSourceKey": "%vlocity_namespace%__Element__c/%vlocity_namespace%__OmniScript__c/SG Quoting/Non-NY/English/MedicalLockDisclaimer_Vision"
}