[
    {
        "%vlocity_namespace%__DomainObjectAPIName__c": "Account",
        "%vlocity_namespace%__DomainObjectCreationOrder__c": 1,
        "%vlocity_namespace%__DomainObjectFieldAPIName__c": "Association_Name__c",
        "%vlocity_namespace%__InterfaceFieldAPIName__c": "Step:TypeAheadAssociations-Block:TypeAheadAssociations",
        "%vlocity_namespace%__IsDisabled__c": false,
        "%vlocity_namespace%__IsRequiredForUpsert__c": false,
        "%vlocity_namespace%__MapId__c": "UpdateExistingAccAndOppCustom582",
        "%vlocity_namespace%__UpsertKey__c": false,
        "Name": "UpdateExistingAccAndOpp",
        "VlocityDataPackType": "SObject",
        "VlocityRecordSObjectType": "%vlocity_namespace%__DRMapItem__c"
    },
    {
        "%vlocity_namespace%__DomainObjectAPIName__c": "Account",
        "%vlocity_namespace%__DomainObjectCreationOrder__c": 1,
        "%vlocity_namespace%__DomainObjectFieldAPIName__c": "Company_State__c",
        "%vlocity_namespace%__InterfaceFieldAPIName__c": "Step:FormulaState",
        "%vlocity_namespace%__IsDisabled__c": false,
        "%vlocity_namespace%__IsRequiredForUpsert__c": false,
        "%vlocity_namespace%__MapId__c": "UpdateExistingAccAndOppCustom8624",
        "%vlocity_namespace%__UpsertKey__c": false,
        "Name": "UpdateExistingAccAndOpp",
        "VlocityDataPackType": "SObject",
        "VlocityRecordSObjectType": "%vlocity_namespace%__DRMapItem__c"
    },
    {
        "%vlocity_namespace%__DomainObjectAPIName__c": "Account",
        "%vlocity_namespace%__DomainObjectCreationOrder__c": 1,
        "%vlocity_namespace%__DomainObjectFieldAPIName__c": "Company_Zip__c",
        "%vlocity_namespace%__InterfaceFieldAPIName__c": "Step:FormulaZip",
        "%vlocity_namespace%__IsDisabled__c": false,
        "%vlocity_namespace%__IsRequiredForUpsert__c": false,
        "%vlocity_namespace%__MapId__c": "UpdateExistingAccAndOppCustom8799",
        "%vlocity_namespace%__UpsertKey__c": false,
        "Name": "UpdateExistingAccAndOpp",
        "VlocityDataPackType": "SObject",
        "VlocityRecordSObjectType": "%vlocity_namespace%__DRMapItem__c"
    },
    {
        "%vlocity_namespace%__DomainObjectAPIName__c": "Account",
        "%vlocity_namespace%__DomainObjectCreationOrder__c": 1,
        "%vlocity_namespace%__DomainObjectFieldAPIName__c": "County__c",
        "%vlocity_namespace%__InterfaceFieldAPIName__c": "Step:FormulaCounty",
        "%vlocity_namespace%__IsDisabled__c": false,
        "%vlocity_namespace%__IsRequiredForUpsert__c": false,
        "%vlocity_namespace%__MapId__c": "UpdateExistingAccAndOppCustom6721",
        "%vlocity_namespace%__UpsertKey__c": false,
        "Name": "UpdateExistingAccAndOpp",
        "VlocityDataPackType": "SObject",
        "VlocityRecordSObjectType": "%vlocity_namespace%__DRMapItem__c"
    },
    {
        "%vlocity_namespace%__DomainObjectAPIName__c": "Account",
        "%vlocity_namespace%__DomainObjectCreationOrder__c": 1,
        "%vlocity_namespace%__DomainObjectFieldAPIName__c": "Employer_EIN__c",
        "%vlocity_namespace%__FormulaOrder__c": 0,
        "%vlocity_namespace%__InterfaceFieldAPIName__c": "Step:TaxID",
        "%vlocity_namespace%__InterfaceObjectName__c": "json",
        "%vlocity_namespace%__IsDisabled__c": false,
        "%vlocity_namespace%__IsRequiredForUpsert__c": false,
        "%vlocity_namespace%__LinkCreatedIndex__c": 0,
        "%vlocity_namespace%__MapId__c": "UpdateExistingAccAndOppCustoma2c0R000000SKA2QAOItem2",
        "%vlocity_namespace%__UpsertKey__c": false,
        "Name": "UpdateExistingAccAndOpp",
        "VlocityDataPackType": "SObject",
        "VlocityRecordSObjectType": "%vlocity_namespace%__DRMapItem__c"
    },
    {
        "%vlocity_namespace%__DomainObjectAPIName__c": "Account",
        "%vlocity_namespace%__DomainObjectCreationOrder__c": 1,
        "%vlocity_namespace%__DomainObjectFieldAPIName__c": "Id",
        "%vlocity_namespace%__FormulaOrder__c": 0,
        "%vlocity_namespace%__InterfaceFieldAPIName__c": "Step:ExistingAccount_Id",
        "%vlocity_namespace%__InterfaceObjectName__c": "json",
        "%vlocity_namespace%__IsDisabled__c": false,
        "%vlocity_namespace%__IsRequiredForUpsert__c": false,
        "%vlocity_namespace%__LinkCreatedIndex__c": 0,
        "%vlocity_namespace%__MapId__c": "UpdateExistingAccAndOppCustoma2c0R000000SKA2QAOItem0",
        "%vlocity_namespace%__UpsertKey__c": true,
        "Name": "UpdateExistingAccAndOpp",
        "VlocityDataPackType": "SObject",
        "VlocityRecordSObjectType": "%vlocity_namespace%__DRMapItem__c"
    },
    {
        "%vlocity_namespace%__DomainObjectAPIName__c": "Account",
        "%vlocity_namespace%__DomainObjectCreationOrder__c": 1,
        "%vlocity_namespace%__DomainObjectFieldAPIName__c": "Name",
        "%vlocity_namespace%__FormulaOrder__c": 0,
        "%vlocity_namespace%__InterfaceFieldAPIName__c": "Step:GroupName",
        "%vlocity_namespace%__InterfaceObjectName__c": "json",
        "%vlocity_namespace%__IsDisabled__c": false,
        "%vlocity_namespace%__IsRequiredForUpsert__c": false,
        "%vlocity_namespace%__LinkCreatedIndex__c": 0,
        "%vlocity_namespace%__MapId__c": "UpdateExistingAccAndOppCustoma2c0R000000SKA2QAOItem1",
        "%vlocity_namespace%__UpsertKey__c": false,
        "Name": "UpdateExistingAccAndOpp",
        "VlocityDataPackType": "SObject",
        "VlocityRecordSObjectType": "%vlocity_namespace%__DRMapItem__c"
    },
    {
        "%vlocity_namespace%__DomainObjectAPIName__c": "Account",
        "%vlocity_namespace%__DomainObjectCreationOrder__c": 1,
        "%vlocity_namespace%__DomainObjectFieldAPIName__c": "Tech_CoverageEffectiveDate__c",
        "%vlocity_namespace%__InterfaceFieldAPIName__c": "CategorySelection:CoverageEffectiveDate",
        "%vlocity_namespace%__IsDisabled__c": false,
        "%vlocity_namespace%__IsRequiredForUpsert__c": false,
        "%vlocity_namespace%__MapId__c": "UpdateExistingAccAndOppCustom2371",
        "%vlocity_namespace%__UpsertKey__c": false,
        "Name": "UpdateExistingAccAndOpp",
        "VlocityDataPackType": "SObject",
        "VlocityRecordSObjectType": "%vlocity_namespace%__DRMapItem__c"
    },
    {
        "%vlocity_namespace%__DomainObjectAPIName__c": "Account",
        "%vlocity_namespace%__DomainObjectCreationOrder__c": 1,
        "%vlocity_namespace%__DomainObjectFieldAPIName__c": "Tech_CoverageOptions__c",
        "%vlocity_namespace%__InterfaceFieldAPIName__c": "CategorySelection:CoverageOptions",
        "%vlocity_namespace%__IsDisabled__c": false,
        "%vlocity_namespace%__IsRequiredForUpsert__c": false,
        "%vlocity_namespace%__MapId__c": "UpdateExistingAccAndOppCustom3869",
        "%vlocity_namespace%__UpsertKey__c": false,
        "Name": "UpdateExistingAccAndOpp",
        "VlocityDataPackType": "SObject",
        "VlocityRecordSObjectType": "%vlocity_namespace%__DRMapItem__c"
    },
    {
        "%vlocity_namespace%__DomainObjectAPIName__c": "Account",
        "%vlocity_namespace%__DomainObjectCreationOrder__c": 1,
        "%vlocity_namespace%__DomainObjectFieldAPIName__c": "Temp_BrokerETIN__c",
        "%vlocity_namespace%__FormulaOrder__c": 0,
        "%vlocity_namespace%__InterfaceFieldAPIName__c": "Step:TypeAheadBroker-Block:BrokerTIN",
        "%vlocity_namespace%__InterfaceObjectName__c": "json",
        "%vlocity_namespace%__IsDisabled__c": false,
        "%vlocity_namespace%__IsRequiredForUpsert__c": false,
        "%vlocity_namespace%__LinkCreatedIndex__c": 0,
        "%vlocity_namespace%__MapId__c": "UpdateExistingAccAndOppCustoma2c0R000000SKA2QAOItem3",
        "%vlocity_namespace%__UpsertKey__c": false,
        "Name": "UpdateExistingAccAndOpp",
        "VlocityDataPackType": "SObject",
        "VlocityRecordSObjectType": "%vlocity_namespace%__DRMapItem__c"
    },
    {
        "%vlocity_namespace%__DomainObjectAPIName__c": "Account",
        "%vlocity_namespace%__DomainObjectCreationOrder__c": 1,
        "%vlocity_namespace%__DomainObjectFieldAPIName__c": "Temp_GeneralAgencyETIN__c",
        "%vlocity_namespace%__FormulaOrder__c": 0,
        "%vlocity_namespace%__InterfaceFieldAPIName__c": "Step:TypeAheadGeneralAgency-Block:GeneralAgencyTIN",
        "%vlocity_namespace%__InterfaceObjectName__c": "json",
        "%vlocity_namespace%__IsDisabled__c": false,
        "%vlocity_namespace%__IsRequiredForUpsert__c": false,
        "%vlocity_namespace%__LinkCreatedIndex__c": 0,
        "%vlocity_namespace%__MapId__c": "UpdateExistingAccAndOppCustoma2c0R000000SKA2QAOItem4",
        "%vlocity_namespace%__UpsertKey__c": false,
        "Name": "UpdateExistingAccAndOpp",
        "VlocityDataPackType": "SObject",
        "VlocityRecordSObjectType": "%vlocity_namespace%__DRMapItem__c"
    },
    {
        "%vlocity_namespace%__DomainObjectAPIName__c": "Account",
        "%vlocity_namespace%__DomainObjectCreationOrder__c": 1,
        "%vlocity_namespace%__DomainObjectFieldAPIName__c": "Temp_PaidAgencyETIN__c",
        "%vlocity_namespace%__FormulaOrder__c": 0,
        "%vlocity_namespace%__InterfaceFieldAPIName__c": "Step:TypeAheadPaidAgency-Block:PaidAgencyTIN",
        "%vlocity_namespace%__InterfaceObjectName__c": "json",
        "%vlocity_namespace%__IsDisabled__c": false,
        "%vlocity_namespace%__IsRequiredForUpsert__c": false,
        "%vlocity_namespace%__LinkCreatedIndex__c": 0,
        "%vlocity_namespace%__MapId__c": "UpdateExistingAccAndOppCustoma2c0R000000SKA2QAOItem5",
        "%vlocity_namespace%__UpsertKey__c": false,
        "Name": "UpdateExistingAccAndOpp",
        "VlocityDataPackType": "SObject",
        "VlocityRecordSObjectType": "%vlocity_namespace%__DRMapItem__c"
    },
    {
        "%vlocity_namespace%__DomainObjectAPIName__c": "Opportunity",
        "%vlocity_namespace%__DomainObjectCreationOrder__c": 2,
        "%vlocity_namespace%__DomainObjectFieldAPIName__c": "AccountId",
        "%vlocity_namespace%__FormulaOrder__c": 0,
        "%vlocity_namespace%__InterfaceObjectName__c": "json",
        "%vlocity_namespace%__IsDisabled__c": false,
        "%vlocity_namespace%__IsRequiredForUpsert__c": false,
        "%vlocity_namespace%__LinkCreatedField__c": "Id",
        "%vlocity_namespace%__LinkCreatedIndex__c": 1,
        "%vlocity_namespace%__MapId__c": "UpdateExistingAccAndOppCustoma2c0R000000SKA2QAOItem10",
        "%vlocity_namespace%__UpsertKey__c": true,
        "Name": "UpdateExistingAccAndOpp",
        "VlocityDataPackType": "SObject",
        "VlocityRecordSObjectType": "%vlocity_namespace%__DRMapItem__c"
    },
    {
        "%vlocity_namespace%__DomainObjectAPIName__c": "Opportunity",
        "%vlocity_namespace%__DomainObjectCreationOrder__c": 2,
        "%vlocity_namespace%__DomainObjectFieldAPIName__c": "CloseDate",
        "%vlocity_namespace%__FormulaOrder__c": 0,
        "%vlocity_namespace%__InterfaceFieldAPIName__c": "Step:CloseDatePrelim",
        "%vlocity_namespace%__InterfaceObjectName__c": "json",
        "%vlocity_namespace%__IsDisabled__c": false,
        "%vlocity_namespace%__IsRequiredForUpsert__c": false,
        "%vlocity_namespace%__LinkCreatedIndex__c": 0,
        "%vlocity_namespace%__MapId__c": "UpdateExistingAccAndOppCustoma2c0R000000SKA2QAOItem12",
        "%vlocity_namespace%__UpsertKey__c": false,
        "Name": "UpdateExistingAccAndOpp",
        "VlocityDataPackType": "SObject",
        "VlocityRecordSObjectType": "%vlocity_namespace%__DRMapItem__c"
    },
    {
        "%vlocity_namespace%__DomainObjectAPIName__c": "Opportunity",
        "%vlocity_namespace%__DomainObjectCreationOrder__c": 2,
        "%vlocity_namespace%__DomainObjectFieldAPIName__c": "GeneralAgency__c",
        "%vlocity_namespace%__InterfaceFieldAPIName__c": "Step:TypeAheadGeneralAgency-Block:GeneralAgencyId",
        "%vlocity_namespace%__IsDisabled__c": false,
        "%vlocity_namespace%__IsRequiredForUpsert__c": false,
        "%vlocity_namespace%__MapId__c": "UpdateExistingAccAndOppCustom3607",
        "%vlocity_namespace%__UpsertKey__c": false,
        "Name": "UpdateExistingAccAndOpp",
        "VlocityDataPackType": "SObject",
        "VlocityRecordSObjectType": "%vlocity_namespace%__DRMapItem__c"
    },
    {
        "%vlocity_namespace%__DefaultValue__c": "Phone",
        "%vlocity_namespace%__DomainObjectAPIName__c": "Opportunity",
        "%vlocity_namespace%__DomainObjectCreationOrder__c": 2,
        "%vlocity_namespace%__DomainObjectFieldAPIName__c": "LeadSource",
        "%vlocity_namespace%__FormulaOrder__c": 0,
        "%vlocity_namespace%__InterfaceObjectName__c": "json",
        "%vlocity_namespace%__IsDisabled__c": false,
        "%vlocity_namespace%__IsRequiredForUpsert__c": false,
        "%vlocity_namespace%__LinkCreatedIndex__c": 0,
        "%vlocity_namespace%__MapId__c": "UpdateExistingAccAndOppCustoma2c0R000000SKA2QAOItem7",
        "%vlocity_namespace%__UpsertKey__c": false,
        "Name": "UpdateExistingAccAndOpp",
        "VlocityDataPackType": "SObject",
        "VlocityRecordSObjectType": "%vlocity_namespace%__DRMapItem__c"
    },
    {
        "%vlocity_namespace%__DomainObjectAPIName__c": "Opportunity",
        "%vlocity_namespace%__DomainObjectCreationOrder__c": 2,
        "%vlocity_namespace%__DomainObjectFieldAPIName__c": "Name",
        "%vlocity_namespace%__FormulaOrder__c": 0,
        "%vlocity_namespace%__InterfaceFieldAPIName__c": "Step:qOpportunityName",
        "%vlocity_namespace%__InterfaceObjectName__c": "json",
        "%vlocity_namespace%__IsDisabled__c": false,
        "%vlocity_namespace%__IsRequiredForUpsert__c": false,
        "%vlocity_namespace%__LinkCreatedIndex__c": 0,
        "%vlocity_namespace%__MapId__c": "UpdateExistingAccAndOppCustoma2c0R000000SKA2QAOItem13",
        "%vlocity_namespace%__UpsertKey__c": true,
        "Name": "UpdateExistingAccAndOpp",
        "VlocityDataPackType": "SObject",
        "VlocityRecordSObjectType": "%vlocity_namespace%__DRMapItem__c"
    },
    {
        "%vlocity_namespace%__DomainObjectAPIName__c": "Opportunity",
        "%vlocity_namespace%__DomainObjectCreationOrder__c": 2,
        "%vlocity_namespace%__DomainObjectFieldAPIName__c": "PaidAgency__c",
        "%vlocity_namespace%__InterfaceFieldAPIName__c": "Step:TypeAheadPaidAgency-Block:PaidAgencyId",
        "%vlocity_namespace%__IsDisabled__c": false,
        "%vlocity_namespace%__IsRequiredForUpsert__c": false,
        "%vlocity_namespace%__MapId__c": "UpdateExistingAccAndOppCustom4188",
        "%vlocity_namespace%__UpsertKey__c": false,
        "Name": "UpdateExistingAccAndOpp",
        "VlocityDataPackType": "SObject",
        "VlocityRecordSObjectType": "%vlocity_namespace%__DRMapItem__c"
    },
    {
        "%vlocity_namespace%__DefaultValue__c": "Opportunity",
        "%vlocity_namespace%__DomainObjectAPIName__c": "Opportunity",
        "%vlocity_namespace%__DomainObjectCreationOrder__c": 2,
        "%vlocity_namespace%__DomainObjectFieldAPIName__c": "RecordTypeId",
        "%vlocity_namespace%__FormulaOrder__c": 0,
        "%vlocity_namespace%__InterfaceObjectName__c": "json",
        "%vlocity_namespace%__IsDisabled__c": false,
        "%vlocity_namespace%__IsRequiredForUpsert__c": false,
        "%vlocity_namespace%__LinkCreatedIndex__c": 0,
        "%vlocity_namespace%__LookupDomainObjectFieldName__c": "SobjectType",
        "%vlocity_namespace%__LookupDomainObjectName__c": "RecordType",
        "%vlocity_namespace%__LookupDomainObjectRequestedFieldName__c": "Id",
        "%vlocity_namespace%__MapId__c": "UpdateExistingAccAndOppCustoma2c0R000000SKA2QAOItem11",
        "%vlocity_namespace%__UpsertKey__c": false,
        "Name": "UpdateExistingAccAndOpp",
        "VlocityDataPackType": "SObject",
        "VlocityRecordSObjectType": "%vlocity_namespace%__DRMapItem__c"
    },
    {
        "%vlocity_namespace%__DefaultValue__c": "SG_Quoting",
        "%vlocity_namespace%__DomainObjectAPIName__c": "Opportunity",
        "%vlocity_namespace%__DomainObjectCreationOrder__c": 2,
        "%vlocity_namespace%__DomainObjectFieldAPIName__c": "RecordTypeId",
        "%vlocity_namespace%__FormulaOrder__c": 0,
        "%vlocity_namespace%__InterfaceObjectName__c": "json",
        "%vlocity_namespace%__IsDisabled__c": false,
        "%vlocity_namespace%__IsRequiredForUpsert__c": false,
        "%vlocity_namespace%__LinkCreatedIndex__c": 0,
        "%vlocity_namespace%__LookupDomainObjectFieldName__c": "DeveloperName",
        "%vlocity_namespace%__LookupDomainObjectName__c": "RecordType",
        "%vlocity_namespace%__LookupDomainObjectRequestedFieldName__c": "Id",
        "%vlocity_namespace%__MapId__c": "UpdateExistingAccAndOppCustoma2c0R000000SKA2QAOItem6",
        "%vlocity_namespace%__UpsertKey__c": false,
        "Name": "UpdateExistingAccAndOpp",
        "VlocityDataPackType": "SObject",
        "VlocityRecordSObjectType": "%vlocity_namespace%__DRMapItem__c"
    },
    {
        "%vlocity_namespace%__DefaultValue__c": "New Opportunity",
        "%vlocity_namespace%__DomainObjectAPIName__c": "Opportunity",
        "%vlocity_namespace%__DomainObjectCreationOrder__c": 2,
        "%vlocity_namespace%__DomainObjectFieldAPIName__c": "StageName",
        "%vlocity_namespace%__FormulaOrder__c": 0,
        "%vlocity_namespace%__InterfaceObjectName__c": "json",
        "%vlocity_namespace%__IsDisabled__c": false,
        "%vlocity_namespace%__IsRequiredForUpsert__c": false,
        "%vlocity_namespace%__LinkCreatedIndex__c": 0,
        "%vlocity_namespace%__MapId__c": "UpdateExistingAccAndOppCustoma2c0R000000SKA2QAOItem9",
        "%vlocity_namespace%__UpsertKey__c": false,
        "Name": "UpdateExistingAccAndOpp",
        "VlocityDataPackType": "SObject",
        "VlocityRecordSObjectType": "%vlocity_namespace%__DRMapItem__c"
    },
    {
        "%vlocity_namespace%__DefaultValue__c": "New Sales",
        "%vlocity_namespace%__DomainObjectAPIName__c": "Opportunity",
        "%vlocity_namespace%__DomainObjectCreationOrder__c": 2,
        "%vlocity_namespace%__DomainObjectFieldAPIName__c": "Type",
        "%vlocity_namespace%__FormulaOrder__c": 0,
        "%vlocity_namespace%__InterfaceObjectName__c": "json",
        "%vlocity_namespace%__IsDisabled__c": false,
        "%vlocity_namespace%__IsRequiredForUpsert__c": false,
        "%vlocity_namespace%__LinkCreatedIndex__c": 0,
        "%vlocity_namespace%__MapId__c": "UpdateExistingAccAndOppCustoma2c0R000000SKA2QAOItem8",
        "%vlocity_namespace%__UpsertKey__c": false,
        "Name": "UpdateExistingAccAndOpp",
        "VlocityDataPackType": "SObject",
        "VlocityRecordSObjectType": "%vlocity_namespace%__DRMapItem__c"
    }
]